pyjeb/__init__.py
pyjeb/controls.py
pyjeb/exception.py
pyjeb/expression.py
pyjeb/main.py
pyjeb/variables.py
pyjeb-1.0.4.dist-info/METADATA
pyjeb-1.0.4.dist-info/WHEEL
pyjeb-1.0.4.dist-info/top_level.txt
pyjeb-1.0.4.dist-info/RECORD
